apiverve_agecalculator/__init__.py
apiverve_agecalculator/apiClient.py
apiverve_agecalculator/exceptions.py
apiverve_agecalculator/setup.py
apiverve_agecalculator/setup_dep.py
apiverve_agecalculator/tests/__init__.py
apiverve_agecalculator/tests/test_api.py
apiverve_agecalculator-1.1.8.dist-info/LICENSE
apiverve_agecalculator-1.1.8.dist-info/METADATA
apiverve_agecalculator-1.1.8.dist-info/WHEEL
apiverve_agecalculator-1.1.8.dist-info/top_level.txt
apiverve_agecalculator-1.1.8.dist-info/RECORD
