Metadata-Version: 2.2
Name: apiverve-agecalculator
Version: 1.1.8
Summary: Age Calculator is a simple tool for calculating age from the date of birth. It returns the calculated age based on the date of birth provided.
Author-email: APIVerve <hello@apiverve.com>
Project-URL: Homepage, https://apiverve.com?utm_source=pypi
Project-URL: Repository, https://github.com/apiverve/agecalculator.Python-API
Project-URL: Documentation, https://docs.apiverve.com/api/agecalculator?utm_source=pypi
Project-URL: Twitter, https://twitter.com/apivervehq
Keywords: age calculator,age calculator api,age calculator tool,age calculator software,age calculator service
Classifier: Development Status :: 5 - Production/Stable
Classifier: Programming Language :: Python :: 3
Classifier: License :: OSI Approved :: MIT License
Classifier: Operating System :: OS Independent
Classifier: Intended Audience :: Developers
Classifier: Intended Audience :: Financial and Insurance Industry
Classifier: Intended Audience :: Healthcare Industry
Classifier: Intended Audience :: Education
Classifier: Intended Audience :: Science/Research
Classifier: Intended Audience :: Information Technology
Classifier: Topic :: Software Development :: Libraries :: Python Modules
Classifier: Topic :: Utilities
Classifier: Topic :: Scientific/Engineering
Classifier: Topic :: Education
Classifier: Topic :: Internet :: WWW/HTTP :: Indexing/Search
Classifier: Topic :: Internet :: WWW/HTTP :: Site Management
Classifier: Topic :: Internet :: WWW/HTTP
Classifier: Topic :: Software Development :: Libraries
Classifier: Topic :: Software Development :: Libraries :: Application Frameworks
Classifier: Topic :: Internet
Classifier: Topic :: Communications
Classifier: Topic :: Office/Business
Classifier: Topic :: Text Processing
Classifier: Topic :: Security
Classifier: Topic :: Database
Classifier: Topic :: Software Development :: Code Generators
Classifier: Topic :: Software Development :: Pre-processors
Classifier: Topic :: Software Development :: Quality Assurance
Classifier: Topic :: Software Development :: Testing
Classifier: Natural Language :: English
Requires-Python: >=3.12
License-File: LICENSE
